{
    "00": "Goblin (regular)",
    "01": "Killer Bee",
    "02": "Nutkin",
    "03": "Stray Cat",
    "04": "Steel Bat",
    "05": "Devil Crab",
    "06": "Stroper",
    "07": "Black Goblin",
    "08": "White Serpent",
    "09": "Moldwynd",
    "0A": "Mani Wizard",
    "0B": "Magic Pot",
    "0C": "Sucker",
    "0D": "Octokraken",
    "0E": "Gatling",
    "0F": "Big Horn",
    "10": "Tatou",
    "11": "Bandersnatch",
    "12": "Garula (regular)",
    "13": "Skeleton",
    "14": "Calcruthl",
    "15": "Undead Husk",
    "16": "Mindflusher",
    "17": "Rock Slug",
    "18": "Gaelicat (regular)",
    "19": "Cockatrice",
    "1A": "Headstone",
    "1B": "Elf Toad (regular)",
    "1C": "Ice Soldier",
    "1D": "Ricard Mage",
    "1E": "Wyvern (regular)",
    "1F": "Pas de Seul",
    "20": "Byblos",
    "21": "Aegir",
    "22": "Zu",
    "23": "Wild Nakk",
    "24": "Grass Tortoise",
    "25": "Silent Bee",
    "26": "Mythril Dragon",
    "27": "Ramuh (boss)",
    "28": "Crew Dust (regular)",
    "29": "Poltergeist",
    "2A": "Motor Trap",
    "2B": "Defeater",
    "2C": "Jackanapes (regular)",
    "2D": "Sergeant (regular)",
    "2E": "Sorcerer",
    "2F": "Cur Nakk (regular)",
    "30": "Gigas",
    "31": "Page 32",
    "32": "Page 64",
    "33": "Page 128",
    "34": "Page 256",
    "35": "Ifrit (boss)",
    "36": "Bomb",
    "37": "Doublizard",
    "38": "Bio Soldier (regular)",
    "39": "Harvester",
    "3A": "Black Flame",
    "3B": "Stone Golem",
    "3C": "Mini Dragon",
    "3D": "Prototype",
    "3E": "Dhorme Chimera (regular)",
    "3F": "Sandboil",
    "40": "Desert Killer",
    "41": "Sand Bear",
    "42": "Ra Mage",
    "43": "Ronkan Knght (regular)",
    "44": "Stone Mask",
    "45": "Enchanted Fan (regular)",
    "46": "Lamia",
    "47": "Archeotoad",
    "48": "Hydra",
    "49": "Ghidra (regular)",
    "4A": "Devilfish",
    "4B": "Treant",
    "4C": "Strapparer",
    "4D": "Tarantula",
    "4E": "Shell Bear",
    "4F": "Tunneller (regular)",
    "50": "Birostris",
    "51": "Fairy Orc",
    "52": "Devourer",
    "53": "Mandrake",
    "54": "Kuza Beast (regular)",
    "55": "Cactus",
    "56": "Sandcrawler",
    "57": "Shield Dragon",
    "58": "Blood Slime",
    "59": "Acrophies",
    "5A": "Moogle Eater",
    "5B": "Lesser Lopros",
    "5C": "Skull Eater",
    "5D": "Aquathorn",
    "5E": "Weresnake",
    "5F": "Kornago",
    "60": "Cursed Being",
    "61": "Undergrounder",
    "62": "Drippy",
    "63": "Lycaon",
    "64": "Bone Dragon (regular)",
    "65": "Poison Eagle",
    "66": "Zombie Dragon (regular)",
    "67": "Golem (1st form)",
    "68": "Neon",
    "69": "Magnetite",
    "6A": "Reflect Knight",
    "6B": "Traveler",
    "6C": "Level Tricker",
    "6D": "Gravitator",
    "6E": "Ziggurat Gigas (regular)",
    "6F": "Cure Beast",
    "70": "Land Turtle",
    "71": "Dechirer",
    "72": "Catoblepas",
    "73": "Mini Magician",
    "74": "Galajelly",
    "75": "Mammon",
    "76": "Imp (regular)",
    "77": "Wyrm",
    "78": "Twin Lizard",
    "79": "Blind Wolf",
    "7A": "Hellraiser",
    "7B": "Reflect Mage",
    "7C": "Magic Dragon",
    "7D": "Black Warlock",
    "7E": "Adamantite Golem (regular)",
    "7F": "Bandercoeurl (regular)",
    "80": "Iron Fist",
    "81": "Blue Dragon",
    "82": "Red Dragon (regular)",
    "83": "Yellow Dragon",
    "84": "Sleepy",
    "85": "Triffid",
    "86": "Hedgehog",
    "87": "Python",
    "88": "Shadow",
    "89": "Elm Gigas",
    "8A": "Pao",
    "8B": "Dark Aspic",
    "8C": "Metamorph",
    "8D": "Unknown (blob 1)",
    "8E": "Desertpede",
    "8F": "Bulette",
    "90": "Sekhmet",
    "91": "Lamia Queen",
    "92": "Rajiformes",
    "93": "Ushabti",
    "94": "Archeosaur",
    "95": "Zephyrus",
    "96": "Exdeath's Soul",
    "97": "Slug",
    "98": "Gloom Widow",
    "99": "Mykale",
    "9A": "Executor",
    "9B": "Oiseaurare (regular)",
    "9C": "Shadow Dancer",
    "9D": "The Damned",
    "9E": "Numb Blade",
    "9F": "Tiny Mage",
    "A0": "Chrono Controller",
    "A1": "Bone Dragon (Golem battle)",
    "A2": "Flaremancer",
    "A3": "Dueling Knight",
    "A4": "Iron Muscles",
    "A5": "Berserker",
    "A6": "Zombie Dragon (Golem battle)",
    "A7": "Druid",
    "A8": "Ironback",
    "A9": "Objet d'Art",
    "AA": "Frost Bull",
    "AB": "Istory Lythos",
    "AC": "Spizzner",
    "AD": "Unknown (slime)",
    "AE": "Unknown (worm)",
    "AF": "Unknown (blob 2)",
    "B0": "Unknown (skeleton)",
    "B1": "Mercury Bat",
    "B2": "Coral",
    "B3": "Tonberry",
    "B4": "Aquagel",
    "B5": "Steel Fist",
    "B6": "Alchymia",
    "B7": "Red Dragon (Alchymia)",
    "B8": "Ghidra (Alchymia)",
    "B9": "Bone Dragon (Alchymia)",
    "BA": "Grenade",
    "BB": "Sword Dancer",
    "BC": "Baldanders",
    "BD": "Death Dealer",
    "BE": "Ankheg",
    "BF": "Ammonite",
    "C0": "Landcrawler",
    "C1": "Lemure",
    "C2": "Parthenope",
    "C3": "Cherie",
    "C4": "White Flame",
    "C5": "Moss Fungus",
    "C6": "Orukat",
    "C7": "Iron Giant",
    "C8": "Death Claw",
    "C9": "King Behemoth",
    "CA": "Farfarello",
    "CB": "Necromancer",
    "CC": "Ninja",
    "CD": "Great Dragon",
    "CE": "Dragon Aevis",
    "CF": "Gorgimera",
    "D0": "Level Checker",
    "D1": "Mindflayer",
    "D2": "Fury",
    "D3": "Crystelle",
    "D4": "Mover",
    "D5": "Crystal Dragon",
    "D6": "Achelon",
    "D7": "Yojimbo",
    "D8": "Gilgamesh (Interdimensional Rift)",
    "D9": "Sahagin",
    "DA": "Thunder Anemone",
    "DB": "Sea Ibis",
    "DC": "Corbett",
    "DD": "Nix",
    "DE": "Water Scorpion",
    "DF": "Vilia",
    "E0": "Gel Fish",
    "E1": "Rukh",
    "E2": "Sea Devil",
    "E3": "Stingray",
    "E4": "??? (Golem)",
    "E5": "Golem (2nd form)",
    "E6": "Chimera",
    "E7": "Shiva (Metamorph)",
    "E8": "Ifrit (Metamorph)",
    "E9": "Ramuh (Metamorph)",
    "EA": "Gaelicat (Metamorph)",
    "EB": "Wyvern (Metamorph)",
    "EC": "Elf Toad (Metamorph)",
    "ED": "Crew Dust (Metamorph)",
    "EE": "Enchanted Fan (Metamorph)",
    "EF": "Zombie Dragon (Metamorph)",
    "F0": "Dhorme Chimera (Zephyrus)",
    "F1": "Adamantite Golem (Zephyrus)",
    "F2": "Ziggurat Gigas (Zephyrus)",
    "F3": "Ronkan Knght (Zephyrus)",
    "F4": "Bio Soldier (Zephyrus)",
    "F5": "Tunneller (Zephyrus)",
    "F6": "Tot Aevis",
    "F7": "Belphegor",
    "F8": "Imp (Castle Exdeath)",
    "F9": "Oiseaurare (Castle Exdeath)",
    "FA": "Jackanapes (Castle Exdeath)",
    "FB": "Gobbledygook",
    "FC": "Gil Turtle",
    "FD": "Omega",
    "FE": "Big Boss",
    "FF": "Enemy_FF",
    "100": "Wing Raptor (1st form)",
    "101": "Wing Raptor (2nd form)",
    "102": "Karlabos",
    "103": "Twintania (2nd form)",
    "104": "Siren (1st form)",
    "105": "Siren (2nd form)",
    "106": "Forza",
    "107": "Magissa",
    "108": "Garula (boss)",
    "109": "Liquid Flame (human form)",
    "10A": "Liquid Flame (hand form)",
    "10B": "Liquid Flame (tornado form)",
    "10C": "Ice Commander",
    "10D": "[Executor] Sandworm",
    "10E": "Hole (Sandworm battle)",
    "10F": "[Orchestrator] Sandworm",
    "110": "Adamantoise",
    "111": "Flame Thrower",
    "112": "Rocket Launcher",
    "113": "Exdeath (tree)",
    "114": "Soul Cannon (boss)",
    "115": "Archeoaevis (1st form)",
    "116": "Archeoaevis (2nd form)",
    "117": "Archeoaevis (3rd form)",
    "118": "Archeoaevis (4th form)",
    "119": "Archeoaevis (5th form)",
    "11A": "Chimera Brain",
    "11B": "Titan",
    "11C": "Purobolos",
    "11D": "Abductor (Bartz solo)",
    "11E": "Gilgamesh (dungeon)",
    "11F": "Merrow",
    "120": "Flying Killer",
    "121": "Little Chariot",
    "122": "Neo Garula",
    "123": "Gilgamesh (Big Bridge)",
    "124": "Tyrannosaur",
    "125": "Shiva (boss)",
    "126": "Abductor (Castle of Bal)",
    "127": "Dragon Pod",
    "128": "Dragon Flower (1st)",
    "129": "Dragon Flower (2nd)",
    "12A": "Dragon Flower (3rd)",
    "12B": "Dragon Flower (4th)",
    "12C": "Dragon Flower (5th)",
    "12D": "Gilgamesh (Xezat's Fleet)",
    "12E": "Enkidu",
    "12F": "Atomos",
    "130": "Fire Crystal",
    "131": "Earth Crystal",
    "132": "Water Crystal",
    "133": "Wind Crystal",
    "134": "Carbuncle (1st form)",
    "135": "Melusine (ending credits)",
    "136": "Gilgamesh (Castle Exdeath, morphed)",
    "137": "Exdeath (Castle Exdeath)",
    "138": "Antlion",
    "139": "Mummy",
    "13A": "Aspis",
    "13B": "Mecha Head",
    "13C": "Melusine (1st form)",
    "13D": "Melusine (2nd form)",
    "13E": "Melusine (3rd form)",
    "13F": "Melusine (4th form)",
    "140": "Odin",
    "141": "Gargoyle",
    "142": "Triton",
    "143": "Nereid",
    "144": "Phobos",
    "145": "Omniscient",
    "146": "Minotaur",
    "147": "Leviathan",
    "148": "Wendigo",
    "149": "Famed Mimic Gogo",
    "14A": "Bahamut",
    "14B": "Jura Aevis",
    "14C": "Halicarnassus",
    "14D": "Exdeath (Galuf solo)",
    "14E": "Neo Exdeath (dummy 1)",
    "14F": "Neo Exdeath (dummy 2)",
    "150": "Goblin (Bartz solo)",
    "151": "Iron Claw",
    "152": "Sergeant (Iron Claw battle)",
    "153": "Cur Nakk (Iron Claw battle)",
    "154": "Cray Claw",
    "155": "Neo Goblin",
    "156": "Calofisteri",
    "157": "Azulmagia",
    "158": "Catastrophe",
    "159": "Necrophobe",
    "15A": "Twintania (1st form)",
    "15B": "Launcher (1st, Soul Cannon battle)",
    "15C": "Launcher (2nd, Soul Cannon battle)",
    "15D": "Gilgamesh (Castle Exdeath, normal)",
    "15E": "Carbuncle (2nd form)",
    "15F": "Grand Mummy",
    "160": "Apanda",
    "161": "Alte Roite",
    "162": "Covert",
    "163": "Abductor (Castle Exdeath)",
    "164": "Bandercoeurl (Phoenix Tower)",
    "165": "Liquid Flame (Phoenix Tower)",
    "166": "Kuza Beast (Phoenix Tower)",
    "167": "Soul Cannon (Phoenix Tower)",
    "168": "Pantera",
    "169": "Shinryu",
    "16A": "Barrier",
    "16B": "Neo Exdeath (top)",
    "16C": "Neo Exdeath (bottom)",
    "16D": "Neo Exdeath (back)",
    "16E": "Neo Exdeath (front)",
    "16F": "Gilgamesh (Necrophobe battle)",
    "170": "UNUSED 0x170",
    "171": "UNUSED 0x171",
    "172": "UNUSED 0x172",
    "173": "UNUSED 0x173",
    "174": "UNUSED 0x174",
    "175": "UNUSED 0x175",
    "176": "UNUSED 0x176",
    "177": "UNUSED 0x177",
    "178": "UNUSED 0x178",
    "179": "UNUSED 0x179",
    "17A": "UNUSED 0x17A",
    "17B": "UNUSED 0x17B",
    "17C": "UNUSED 0x17C",
    "17D": "UNUSED 0x17D",
    "17E": "UNUSED 0x17E",
    "17F": "UNUSED 0x17F"
}
