{
    "enemy_id": "231",
    "enemy_name": "Earth Crystal",
    "raw": "020DB80BFECFFE00000000FEFC808081FFFF",
    "active_rules": [
        {
            "conditions": [
                {
                    "condition": "HP lower than threshold",
                    "target": "self",
                    "hp_threshold": 3000
                }
            ],
            "actions": {
                "Turn #1": [
                    "Ability: Earth Shaker"
                ]
            }
        },
        {
            "conditions": [
                "Unconditional"
            ],
            "actions": {
                "Turn #1": [
                    {
                        "action": "Random selection",
                        "first_choice": "Ability: !Attack",
                        "second_choice": "Ability: !Attack",
                        "third_choice": "Special: Critical Attack"
                    }
                ]
            }
        }
    ],
    "reactive_rules": []
}