{
    "enemy_id": "2E",
    "enemy_name": "Sorcerer",
    "raw": "00000000FEFC1A8080FC298080FFFF",
    "active_rules": [
        {
            "conditions": [
                "Unconditional"
            ],
            "actions": {
                "Turn #1": [
                    {
                        "action": "Random selection",
                        "first_choice": "Ability: Confuse",
                        "second_choice": "Ability: !Attack",
                        "third_choice": "Ability: !Attack"
                    }
                ],
                "Turn #2": [
                    {
                        "action": "Random selection",
                        "first_choice": "Ability: Toad",
                        "second_choice": "Ability: !Attack",
                        "third_choice": "Ability: !Attack"
                    }
                ]
            }
        }
    ],
    "reactive_rules": []
}