{
    "enemy_id": "A6",
    "enemy_name": "Zombie Dragon (Golem battle)",
    "raw": "03000102FEFCB6B681FE0500F020FEFDF40102E7FE0500F060FEFDF40102E7FE03000101FEFDF305F0FC808081FDF305F0FC808081FDF305F0FC809881FE00000000FEFDF40101E7FFFF",
    "active_rules": [
        {
            "conditions": [
                {
                    "condition": "Variable check",
                    "match_type": "All parameters match",
                    "explanation": "variable == value",
                    "var_id": "Var_01",
                    "value_to_match": 2
                }
            ],
            "actions": {
                "Turn #1": [
                    {
                        "action": "Random selection",
                        "first_choice": "Ability: Poison Breath",
                        "second_choice": "Ability: Poison Breath",
                        "third_choice": "Special: Critical Attack"
                    }
                ]
            }
        },
        {
            "conditions": [
                {
                    "condition": "Enemy slots",
                    "match_type": "All parameters match",
                    "explanation": "visible enemies only in these slots",
                    "enemy_slots": [
                        "#3"
                    ]
                }
            ],
            "actions": {
                "Turn #1": [
                    {
                        "action": "AI command",
                        "type": "Set variable",
                        "var_id": "Var_01",
                        "value": 2
                    },
                    "Ability: [Flip sprite horizontally]"
                ]
            }
        },
        {
            "conditions": [
                {
                    "condition": "Enemy slots",
                    "match_type": "All parameters match",
                    "explanation": "visible enemies only in these slots",
                    "enemy_slots": [
                        "#2, #3"
                    ]
                }
            ],
            "actions": {
                "Turn #1": [
                    {
                        "action": "AI command",
                        "type": "Set variable",
                        "var_id": "Var_01",
                        "value": 2
                    },
                    "Ability: [Flip sprite horizontally]"
                ]
            }
        },
        {
            "conditions": [
                {
                    "condition": "Variable check",
                    "match_type": "All parameters match",
                    "explanation": "variable == value",
                    "var_id": "Var_01",
                    "value_to_match": 1
                }
            ],
            "actions": {
                "Turn #1": [
                    {
                        "action": "AI command",
                        "type": "Set target",
                        "target": "The enemy in slot #1"
                    },
                    {
                        "action": "Random selection",
                        "first_choice": "Ability: !Attack",
                        "second_choice": "Ability: !Attack",
                        "third_choice": "Special: Critical Attack"
                    }
                ],
                "Turn #2": [
                    {
                        "action": "AI command",
                        "type": "Set target",
                        "target": "The enemy in slot #1"
                    },
                    {
                        "action": "Random selection",
                        "first_choice": "Ability: !Attack",
                        "second_choice": "Ability: !Attack",
                        "third_choice": "Special: Critical Attack"
                    }
                ],
                "Turn #3": [
                    {
                        "action": "AI command",
                        "type": "Set target",
                        "target": "The enemy in slot #1"
                    },
                    {
                        "action": "Random selection",
                        "first_choice": "Ability: !Attack",
                        "second_choice": "Ability: Vampire",
                        "third_choice": "Special: Critical Attack"
                    }
                ]
            }
        },
        {
            "conditions": [
                "Unconditional"
            ],
            "actions": {
                "Turn #1": [
                    {
                        "action": "AI command",
                        "type": "Set variable",
                        "var_id": "Var_01",
                        "value": 1
                    },
                    "Ability: [Flip sprite horizontally]"
                ]
            }
        }
    ],
    "reactive_rules": []
}